rVADfast/__init__.py
rVADfast/rVADfast.py
rVADfast/legacy_files/__init__.py
rVADfast/legacy_files/rVAD_fast.py
rVADfast/legacy_files/rVAD_fast_stream.py
rVADfast/legacy_files/speechproc.py
rVADfast/process/__init__.py
rVADfast/process/process.py
rVADfast/speechproc/__init__.py
rVADfast/speechproc/speechproc.py
rvadfast-0.0.5.dist-info/licenses/LICENSE
rvadfast-0.0.5.dist-info/METADATA
rvadfast-0.0.5.dist-info/WHEEL
rvadfast-0.0.5.dist-info/entry_points.txt
rvadfast-0.0.5.dist-info/top_level.txt
rvadfast-0.0.5.dist-info/RECORD
