Metadata-Version: 2.4
Name: rVADfast
Version: 0.0.5
Summary: rVADfast - a fast and robust unsupervised VAD
Author-email: Zheng-Hua Tan <zt@es.aau.dk>, Achintya Kumar Sarkar <sarkar.achintya@gmail.com>, Holger Severin Bovbjerg <hsbo@es.aau.dk>
Maintainer-email: Holger Severin Bovbjerg <hsbo@es.aau.dk>, Zheng-Hua Tan <zt@es.aau.dk>
License: MIT License
Project-URL: Homepage, https://github.com/zhenghuatan/rVADfast/
Project-URL: Repository, https://github.com/zhenghuatan/rVADfast.git
Project-URL: Issues, https://github.com/zhenghuatan/rVADfast/issues
Project-URL: Source, https://github.com/zhenghuatan/rVADfast/
Keywords: Audio,Tools,VAD,Speech,Speech Processing
Classifier: Development Status :: 3 - Alpha
Classifier: Intended Audience :: Science/Research
Classifier: Intended Audience :: Developers
Classifier: Programming Language :: Python :: 3
Classifier: Programming Language :: Python :: 3.8
Classifier: Programming Language :: Python :: 3.9
Classifier: Programming Language :: Python :: 3.10
Classifier: Programming Language :: Python :: 3.11
Classifier: Operating System :: OS Independent
Classifier: Topic :: Scientific/Engineering
Classifier: Topic :: Multimedia :: Sound/Audio
Requires-Python: >=3.8
License-File: LICENSE
Requires-Dist: numpy>=1.23.5
Requires-Dist: scipy>=1.10.0
Requires-Dist: audiofile>=1.1.1
Requires-Dist: tqdm>=4.64.1
Dynamic: license-file
